<?xml version="1.0" encoding="utf-8"?>
<Document>
  <Engineering version="V15.1" />
  <DocumentInfo>
    <Created>2020-12-23T11:16:33.2864918Z</Created>
    <ExportSetting>WithDefaults, WithReadOnly</ExportSetting>
    <InstalledProducts>
      <Product>
        <DisplayName>Totally Integrated Automation Portal</DisplayName>
        <DisplayVersion>V15.1 Update 3</DisplayVersion>
      </Product>
      <OptionPackage>
        <DisplayName>TIA Portal Openness</DisplayName>
        <DisplayVersion>V15.1</DisplayVersion>
      </OptionPackage>
      <Product>
        <DisplayName>STEP 7 Professional</DisplayName>
        <DisplayVersion>V15.1 Update 3</DisplayVersion>
      </Product>
      <Product>
        <DisplayName>WinCC Advanced</DisplayName>
        <DisplayVersion>V15.1 Update 3</DisplayVersion>
      </Product>
    </InstalledProducts>
  </DocumentInfo>
  <SW.Blocks.GlobalDB ID="0">
    <AttributeList>
      <AutoNumber>false</AutoNumber>
      <CodeModifiedDate ReadOnly="true">2020-12-23T11:16:22.2079236Z</CodeModifiedDate>
      <CompileDate ReadOnly="true">2020-12-23T11:16:23.5925798Z</CompileDate>
      <CreationDate ReadOnly="true">2020-12-23T11:14:57.9258238Z</CreationDate>
      <DBAccessibleFromOPCUA>true</DBAccessibleFromOPCUA>
      <DownloadWithoutReinit ReadOnly="true">false</DownloadWithoutReinit>
      <HeaderAuthor />
      <HeaderFamily />
      <HeaderName />
      <HeaderVersion>0.1</HeaderVersion>
      <Interface><Sections xmlns="http://www.siemens.com/automation/Openness/SW/Interface/v3">
  <Section Name="Static">
	{MEMBERS}
  </Section>
</Sections></Interface>
      <InterfaceModifiedDate ReadOnly="true">2020-12-23T11:16:22.2079236Z</InterfaceModifiedDate>
      <IsConsistent ReadOnly="true">true</IsConsistent>
      <IsKnowHowProtected ReadOnly="true">false</IsKnowHowProtected>
      <IsOnlyStoredInLoadMemory>false</IsOnlyStoredInLoadMemory>
      <IsPLCDB ReadOnly="true">false</IsPLCDB>
      <IsRetainMemResEnabled>false</IsRetainMemResEnabled>
      <IsWriteProtectedInAS>false</IsWriteProtectedInAS>
      <MemoryLayout>Optimized</MemoryLayout>
      <MemoryReserve>100</MemoryReserve>
      <ModifiedDate ReadOnly="true">2020-12-23T11:16:22.2079236Z</ModifiedDate>
      <Name>DBVALVES</Name>
      <Number>1330</Number>
      <ParameterModified ReadOnly="true">2020-12-23T11:16:22.2079236Z</ParameterModified>
      <ProgrammingLanguage>DB</ProgrammingLanguage>
      <StructureModified ReadOnly="true">2020-12-23T11:16:22.2079236Z</StructureModified>
    </AttributeList>
    <ObjectList>
      <MultilingualText ID="1" CompositionName="Comment">
        <ObjectList>
          <MultilingualTextItem ID="2" CompositionName="Items">
            <AttributeList>
              <Culture>en-US</Culture>
              <Text />
            </AttributeList>
          </MultilingualTextItem>
          <MultilingualTextItem ID="3" CompositionName="Items">
            <AttributeList>
              <Culture>pl-PL</Culture>
              <Text />
            </AttributeList>
          </MultilingualTextItem>
        </ObjectList>
      </MultilingualText>
      <MultilingualText ID="4" CompositionName="Title">
        <ObjectList>
          <MultilingualTextItem ID="5" CompositionName="Items">
            <AttributeList>
              <Culture>en-US</Culture>
              <Text />
            </AttributeList>
          </MultilingualTextItem>
          <MultilingualTextItem ID="6" CompositionName="Items">
            <AttributeList>
              <Culture>pl-PL</Culture>
              <Text />
            </AttributeList>
          </MultilingualTextItem>
        </ObjectList>
      </MultilingualText>
    </ObjectList>
  </SW.Blocks.GlobalDB>
</Document>